<?xml version="1.0" encoding="UTF-8"?>
<objects serializationModel="Studio.02.02.00">
	<object class="MixerReturn" id="{da1f2c81-04e6-4810-8123-d34d0efabd06}">
		<property name="name">
			<value>Reverb</value>
		</property>
		<relationship name="effectChain">
			<destination>{bae1d797-842e-425f-94f8-fb30cb89a0e1}</destination>
		</relationship>
		<relationship name="panner">
			<destination>{db7aa638-eb50-415a-b53b-611f87478b73}</destination>
		</relationship>
		<relationship name="output">
			<destination>{a31f313b-4259-45a0-b333-c4be875a028b}</destination>
		</relationship>
	</object>
	<object class="MixerBusEffectChain" id="{bae1d797-842e-425f-94f8-fb30cb89a0e1}">
		<relationship name="effects">
			<destination>{09782a79-cf2f-4de7-af84-7635394c9b3e}</destination>
		</relationship>
	</object>
	<object class="MixerBusPanner" id="{db7aa638-eb50-415a-b53b-611f87478b73}" />
	<object class="MixerBusFader" id="{09782a79-cf2f-4de7-af84-7635394c9b3e}" />
</objects>
